{
  "schemaVersion": "v1",
  "productId": "B0FGXR4X4T",
  "status": "draft",
  "titleZh": "Winado Licensed Chevrolet Colorado Electric Car for Kids, 12V Ride on Toys for Toddlers with Remote Control, Battery Powered",
  "titleEn": "Winado Licensed Chevrolet Colorado Electric Car for Kids, 12V Ride on Toys for Toddlers with Remote Control, Battery Powered",
  "subtitleZh": "",
  "subtitleEn": "",
  "highlightsZh": [],
  "highlightsEn": [],
  "tags": [],
  "scenarioIds": [],
  "editorNote": "",
  "publishPriority": 0,
  "isVisible": false,
  "opsScore": null,
  "opsLabel": "",
  "recommendationReasonZh": "",
  "recommendationReasonEn": "",
  "seo": {
    "titleZh": "",
    "titleEn": "",
    "descZh": "",
    "descEn": "",
    "keywordsZh": [],
    "keywordsEn": []
  },
  "updatedAt": "2026-07-01T21:38:46.679Z",
  "updatedBy": "ops-staging"
}
