{
  "schemaVersion": "v1",
  "productId": "B01LY46WJN",
  "status": "draft",
  "titleZh": "Little Tikes Cozy Coupe Dinosaur – Amazon Exclusive Large, Green",
  "titleEn": "Little Tikes Cozy Coupe Dinosaur – Amazon Exclusive Large, Green",
  "subtitleZh": "",
  "subtitleEn": "",
  "highlightsZh": [],
  "highlightsEn": [],
  "tags": [],
  "scenarioIds": [],
  "editorNote": "",
  "publishPriority": 0,
  "isVisible": false,
  "opsScore": null,
  "opsLabel": "",
  "recommendationReasonZh": "",
  "recommendationReasonEn": "",
  "seo": {
    "titleZh": "",
    "titleEn": "",
    "descZh": "",
    "descEn": "",
    "keywordsZh": [],
    "keywordsEn": []
  },
  "updatedAt": "2026-07-01T21:39:03.782Z",
  "updatedBy": "ops-staging"
}
